{
  "openapi": "3.0.1",
  "info": {
    "title": "SCBS.APIServices",
    "version": "1.0"
  },
  "paths": {
    "/api/Schedule": {
      "get": {
        "tags": [
          "Schedule"
        ],
        "responses": {
          "200": {
            "description": "OK",
            "content": {
              "text/plain": {
                "schema": {
                  "type": "array",
                  "items": {
                    "$ref": "#/components/schemas/Schedule"
                  }
                }
              },
              "application/json": {
                "schema": {
                  "type": "array",
                  "items": {
                    "$ref": "#/components/schemas/Schedule"
                  }
                }
              },
              "text/json": {
                "schema": {
                  "type": "array",
                  "items": {
                    "$ref": "#/components/schemas/Schedule"
                  }
                }
              }
            }
          }
        }
      },
      "post": {
        "tags": [
          "Schedule"
        ],
        "requestBody": {
          "content": {
            "application/json": {
              "schema": {
                "$ref": "#/components/schemas/Schedule"
              }
            },
            "text/json": {
              "schema": {
                "$ref": "#/components/schemas/Schedule"
              }
            },
            "application/*+json": {
              "schema": {
                "$ref": "#/components/schemas/Schedule"
              }
            }
          }
        },
        "responses": {
          "200": {
            "description": "OK",
            "content": {
              "text/plain": {
                "schema": {
                  "type": "integer",
                  "format": "int32"
                }
              },
              "application/json": {
                "schema": {
                  "type": "integer",
                  "format": "int32"
                }
              },
              "text/json": {
                "schema": {
                  "type": "integer",
                  "format": "int32"
                }
              }
            }
          }
        }
      }
    },
    "/api/Schedule/{id}": {
      "get": {
        "tags": [
          "Schedule"
        ],
        "parameters": [
          {
            "name": "id",
            "in": "path",
            "required": true,
            "schema": {
              "type": "string",
              "format": "uuid"
            }
          }
        ],
        "responses": {
          "200": {
            "description": "OK",
            "content": {
              "text/plain": {
                "schema": {
                  "$ref": "#/components/schemas/Schedule"
                }
              },
              "application/json": {
                "schema": {
                  "$ref": "#/components/schemas/Schedule"
                }
              },
              "text/json": {
                "schema": {
                  "$ref": "#/components/schemas/Schedule"
                }
              }
            }
          }
        }
      },
      "put": {
        "tags": [
          "Schedule"
        ],
        "parameters": [
          {
            "name": "id",
            "in": "path",
            "required": true,
            "schema": {
              "type": "string"
            }
          }
        ],
        "requestBody": {
          "content": {
            "application/json": {
              "schema": {
                "$ref": "#/components/schemas/Schedule"
              }
            },
            "text/json": {
              "schema": {
                "$ref": "#/components/schemas/Schedule"
              }
            },
            "application/*+json": {
              "schema": {
                "$ref": "#/components/schemas/Schedule"
              }
            }
          }
        },
        "responses": {
          "200": {
            "description": "OK",
            "content": {
              "text/plain": {
                "schema": {
                  "type": "integer",
                  "format": "int32"
                }
              },
              "application/json": {
                "schema": {
                  "type": "integer",
                  "format": "int32"
                }
              },
              "text/json": {
                "schema": {
                  "type": "integer",
                  "format": "int32"
                }
              }
            }
          }
        }
      },
      "delete": {
        "tags": [
          "Schedule"
        ],
        "parameters": [
          {
            "name": "id",
            "in": "path",
            "required": true,
            "schema": {
              "type": "string",
              "format": "uuid"
            }
          }
        ],
        "responses": {
          "200": {
            "description": "OK",
            "content": {
              "text/plain": {
                "schema": {
                  "type": "boolean"
                }
              },
              "application/json": {
                "schema": {
                  "type": "boolean"
                }
              },
              "text/json": {
                "schema": {
                  "type": "boolean"
                }
              }
            }
          }
        }
      }
    },
    "/api/Schedule/{workDate}/{status}": {
      "get": {
        "tags": [
          "Schedule"
        ],
        "parameters": [
          {
            "name": "workDate",
            "in": "path",
            "required": true,
            "schema": {
              "type": "string",
              "format": "date-time"
            }
          },
          {
            "name": "status",
            "in": "path",
            "required": true,
            "schema": {
              "type": "string"
            }
          }
        ],
        "responses": {
          "200": {
            "description": "OK",
            "content": {
              "text/plain": {
                "schema": {
                  "type": "array",
                  "items": {
                    "$ref": "#/components/schemas/Schedule"
                  }
                }
              },
              "application/json": {
                "schema": {
                  "type": "array",
                  "items": {
                    "$ref": "#/components/schemas/Schedule"
                  }
                }
              },
              "text/json": {
                "schema": {
                  "type": "array",
                  "items": {
                    "$ref": "#/components/schemas/Schedule"
                  }
                }
              }
            }
          }
        }
      }
    },
    "/api/User": {
      "get": {
        "tags": [
          "User"
        ],
        "responses": {
          "200": {
            "description": "OK",
            "content": {
              "text/plain": {
                "schema": {
                  "type": "array",
                  "items": {
                    "$ref": "#/components/schemas/User"
                  }
                }
              },
              "application/json": {
                "schema": {
                  "type": "array",
                  "items": {
                    "$ref": "#/components/schemas/User"
                  }
                }
              },
              "text/json": {
                "schema": {
                  "type": "array",
                  "items": {
                    "$ref": "#/components/schemas/User"
                  }
                }
              }
            }
          }
        }
      },
      "post": {
        "tags": [
          "User"
        ],
        "requestBody": {
          "content": {
            "application/json": {
              "schema": {
                "$ref": "#/components/schemas/User"
              }
            },
            "text/json": {
              "schema": {
                "$ref": "#/components/schemas/User"
              }
            },
            "application/*+json": {
              "schema": {
                "$ref": "#/components/schemas/User"
              }
            }
          }
        },
        "responses": {
          "200": {
            "description": "OK",
            "content": {
              "text/plain": {
                "schema": {
                  "type": "integer",
                  "format": "int32"
                }
              },
              "application/json": {
                "schema": {
                  "type": "integer",
                  "format": "int32"
                }
              },
              "text/json": {
                "schema": {
                  "type": "integer",
                  "format": "int32"
                }
              }
            }
          }
        }
      },
      "put": {
        "tags": [
          "User"
        ],
        "requestBody": {
          "content": {
            "application/json": {
              "schema": {
                "$ref": "#/components/schemas/User"
              }
            },
            "text/json": {
              "schema": {
                "$ref": "#/components/schemas/User"
              }
            },
            "application/*+json": {
              "schema": {
                "$ref": "#/components/schemas/User"
              }
            }
          }
        },
        "responses": {
          "200": {
            "description": "OK",
            "content": {
              "text/plain": {
                "schema": {
                  "type": "integer",
                  "format": "int32"
                }
              },
              "application/json": {
                "schema": {
                  "type": "integer",
                  "format": "int32"
                }
              },
              "text/json": {
                "schema": {
                  "type": "integer",
                  "format": "int32"
                }
              }
            }
          }
        }
      }
    },
    "/api/User/{id}": {
      "get": {
        "tags": [
          "User"
        ],
        "parameters": [
          {
            "name": "id",
            "in": "path",
            "required": true,
            "schema": {
              "type": "string",
              "format": "uuid"
            }
          }
        ],
        "responses": {
          "200": {
            "description": "OK",
            "content": {
              "text/plain": {
                "schema": {
                  "$ref": "#/components/schemas/User"
                }
              },
              "application/json": {
                "schema": {
                  "$ref": "#/components/schemas/User"
                }
              },
              "text/json": {
                "schema": {
                  "$ref": "#/components/schemas/User"
                }
              }
            }
          }
        }
      },
      "delete": {
        "tags": [
          "User"
        ],
        "parameters": [
          {
            "name": "id",
            "in": "path",
            "required": true,
            "schema": {
              "type": "string",
              "format": "uuid"
            }
          }
        ],
        "responses": {
          "200": {
            "description": "OK",
            "content": {
              "text/plain": {
                "schema": {
                  "type": "boolean"
                }
              },
              "application/json": {
                "schema": {
                  "type": "boolean"
                }
              },
              "text/json": {
                "schema": {
                  "type": "boolean"
                }
              }
            }
          }
        }
      }
    },
    "/api/User/{username}/{email}/{fullName}": {
      "get": {
        "tags": [
          "User"
        ],
        "parameters": [
          {
            "name": "username",
            "in": "path",
            "required": true,
            "schema": {
              "type": "string"
            }
          },
          {
            "name": "email",
            "in": "path",
            "required": true,
            "schema": {
              "type": "string"
            }
          },
          {
            "name": "fullName",
            "in": "path",
            "required": true,
            "schema": {
              "type": "string"
            }
          }
        ],
        "responses": {
          "200": {
            "description": "OK",
            "content": {
              "text/plain": {
                "schema": {
                  "type": "array",
                  "items": {
                    "$ref": "#/components/schemas/User"
                  }
                }
              },
              "application/json": {
                "schema": {
                  "type": "array",
                  "items": {
                    "$ref": "#/components/schemas/User"
                  }
                }
              },
              "text/json": {
                "schema": {
                  "type": "array",
                  "items": {
                    "$ref": "#/components/schemas/User"
                  }
                }
              }
            }
          }
        }
      }
    },
    "/api/UserAccount/Login": {
      "post": {
        "tags": [
          "UserAccount"
        ],
        "requestBody": {
          "content": {
            "application/json": {
              "schema": {
                "$ref": "#/components/schemas/LoginReqeust"
              }
            },
            "text/json": {
              "schema": {
                "$ref": "#/components/schemas/LoginReqeust"
              }
            },
            "application/*+json": {
              "schema": {
                "$ref": "#/components/schemas/LoginReqeust"
              }
            }
          }
        },
        "responses": {
          "200": {
            "description": "OK"
          }
        }
      }
    },
    "/WeatherForecast": {
      "get": {
        "tags": [
          "WeatherForecast"
        ],
        "operationId": "GetWeatherForecast",
        "responses": {
          "200": {
            "description": "OK",
            "content": {
              "text/plain": {
                "schema": {
                  "type": "array",
                  "items": {
                    "$ref": "#/components/schemas/WeatherForecast"
                  }
                }
              },
              "application/json": {
                "schema": {
                  "type": "array",
                  "items": {
                    "$ref": "#/components/schemas/WeatherForecast"
                  }
                }
              },
              "text/json": {
                "schema": {
                  "type": "array",
                  "items": {
                    "$ref": "#/components/schemas/WeatherForecast"
                  }
                }
              }
            }
          }
        }
      }
    }
  },
  "components": {
    "schemas": {
      "LoginReqeust": {
        "type": "object",
        "properties": {
          "userName": {
            "type": "string",
            "nullable": true
          },
          "password": {
            "type": "string",
            "nullable": true
          }
        },
        "additionalProperties": false
      },
      "Schedule": {
        "type": "object",
        "properties": {
          "id": {
            "type": "string",
            "format": "uuid"
          },
          "userId": {
            "type": "string",
            "format": "uuid"
          },
          "workDate": {
            "type": "string",
            "format": "date-time"
          },
          "status": {
            "type": "string",
            "nullable": true
          },
          "createdAt": {
            "type": "string",
            "format": "date-time",
            "nullable": true
          },
          "updatedAt": {
            "type": "string",
            "format": "date-time",
            "nullable": true
          },
          "user": {
            "$ref": "#/components/schemas/User"
          }
        },
        "additionalProperties": false
      },
      "User": {
        "type": "object",
        "properties": {
          "id": {
            "type": "string",
            "format": "uuid"
          },
          "username": {
            "type": "string",
            "nullable": true
          },
          "fullName": {
            "type": "string",
            "nullable": true
          },
          "password": {
            "type": "string",
            "nullable": true
          },
          "email": {
            "type": "string",
            "nullable": true
          },
          "avatar": {
            "type": "string",
            "nullable": true
          },
          "phone": {
            "type": "string",
            "nullable": true
          },
          "gender": {
            "type": "string",
            "nullable": true
          },
          "role": {
            "type": "string",
            "nullable": true
          },
          "status": {
            "type": "string",
            "nullable": true
          },
          "rating": {
            "type": "number",
            "format": "double",
            "nullable": true
          },
          "createdAt": {
            "type": "string",
            "format": "date-time",
            "nullable": true
          },
          "updatedAt": {
            "type": "string",
            "format": "date-time",
            "nullable": true
          },
          "schedules": {
            "type": "array",
            "items": {
              "$ref": "#/components/schemas/Schedule"
            },
            "nullable": true
          }
        },
        "additionalProperties": false
      },
      "WeatherForecast": {
        "type": "object",
        "properties": {
          "date": {
            "type": "string",
            "format": "date"
          },
          "temperatureC": {
            "type": "integer",
            "format": "int32"
          },
          "temperatureF": {
            "type": "integer",
            "format": "int32",
            "readOnly": true
          },
          "summary": {
            "type": "string",
            "nullable": true
          }
        },
        "additionalProperties": false
      }
    },
    "securitySchemes": {
      "Bearer": {
        "type": "http",
        "description": "Please enter a valid token",
        "scheme": "Bearer",
        "bearerFormat": "JWT"
      }
    }
  },
  "security": [
    {
      "Bearer": [ ]
    }
  ]
}